prashpyutil/__init__.py
prashpyutil/__version__.py
prashpyutil/sum.py
prashpyutil-1.0.0.dist-info/LICENSE
prashpyutil-1.0.0.dist-info/METADATA
prashpyutil-1.0.0.dist-info/WHEEL
prashpyutil-1.0.0.dist-info/top_level.txt
prashpyutil-1.0.0.dist-info/RECORD
